{
  "field_1331+305=3C286": {
    "total": {
      "flagged": 131043920.0,
      "total": 485941248.0
    },
    "spw": {
      "0": {
        "flagged": 5272808.0,
        "total": 15185664.0
      },
      "1": {
        "flagged": 3553472.0,
        "total": 15185664.0
      },
      "10": {
        "flagged": 6026496.0,
        "total": 15185664.0
      },
      "11": {
        "flagged": 3497504.0,
        "total": 15185664.0
      },
      "12": {
        "flagged": 3502604.0,
        "total": 15185664.0
      },
      "13": {
        "flagged": 3495660.0,
        "total": 15185664.0
      },
      "14": {
        "flagged": 3492164.0,
        "total": 15185664.0
      },
      "15": {
        "flagged": 5257520.0,
        "total": 15185664.0
      },
      "16": {
        "flagged": 5303528.0,
        "total": 15185664.0
      },
      "17": {
        "flagged": 3491520.0,
        "total": 15185664.0
      },
      "18": {
        "flagged": 3491312.0,
        "total": 15185664.0
      },
      "19": {
        "flagged": 3494388.0,
        "total": 15185664.0
      },
      "2": {
        "flagged": 3534988.0,
        "total": 15185664.0
      },
      "20": {
        "flagged": 3536424.0,
        "total": 15185664.0
      },
      "21": {
        "flagged": 3721744.0,
        "total": 15185664.0
      },
      "22": {
        "flagged": 4027468.0,
        "total": 15185664.0
      },
      "23": {
        "flagged": 4527400.0,
        "total": 15185664.0
      },
      "24": {
        "flagged": 4769724.0,
        "total": 15185664.0
      },
      "25": {
        "flagged": 3930208.0,
        "total": 15185664.0
      },
      "26": {
        "flagged": 3934092.0,
        "total": 15185664.0
      },
      "27": {
        "flagged": 3736844.0,
        "total": 15185664.0
      },
      "28": {
        "flagged": 5141280.0,
        "total": 15185664.0
      },
      "29": {
        "flagged": 5789588.0,
        "total": 15185664.0
      },
      "3": {
        "flagged": 3628236.0,
        "total": 15185664.0
      },
      "30": {
        "flagged": 4082612.0,
        "total": 15185664.0
      },
      "31": {
        "flagged": 5597524.0,
        "total": 15185664.0
      },
      "4": {
        "flagged": 3544064.0,
        "total": 15185664.0
      },
      "5": {
        "flagged": 3580972.0,
        "total": 15185664.0
      },
      "6": {
        "flagged": 3534608.0,
        "total": 15185664.0
      },
      "7": {
        "flagged": 3514028.0,
        "total": 15185664.0
      },
      "8": {
        "flagged": 3522276.0,
        "total": 15185664.0
      },
      "9": {
        "flagged": 3510864.0,
        "total": 15185664.0
      }
    },
    "antenna": {
      "ea01": {
        "flagged": 10345788.0,
        "total": 35995648.0
      },
      "ea02": {
        "flagged": 10555256.0,
        "total": 35995648.0
      },
      "ea03": {
        "flagged": 9352256.0,
        "total": 35995648.0
      },
      "ea04": {
        "flagged": 9654696.0,
        "total": 35995648.0
      },
      "ea05": {
        "flagged": 9536060.0,
        "total": 35995648.0
      },
      "ea06": {
        "flagged": 12604192.0,
        "total": 35995648.0
      },
      "ea07": {
        "flagged": 10108584.0,
        "total": 35995648.0
      },
      "ea08": {
        "flagged": 9481916.0,
        "total": 35995648.0
      },
      "ea09": {
        "flagged": 10188272.0,
        "total": 35995648.0
      },
      "ea10": {
        "flagged": 9532644.0,
        "total": 35995648.0
      },
      "ea11": {
        "flagged": 9386616.0,
        "total": 35995648.0
      },
      "ea12": {
        "flagged": 9275984.0,
        "total": 35995648.0
      },
      "ea13": {
        "flagged": 9262288.0,
        "total": 35995648.0
      },
      "ea14": {
        "flagged": 10046108.0,
        "total": 35995648.0
      },
      "ea15": {
        "flagged": 9224840.0,
        "total": 35995648.0
      },
      "ea16": {
        "flagged": 10277048.0,
        "total": 35995648.0
      },
      "ea17": {
        "flagged": 9447320.0,
        "total": 35995648.0
      },
      "ea18": {
        "flagged": 9379960.0,
        "total": 35995648.0
      },
      "ea19": {
        "flagged": 9235304.0,
        "total": 35995648.0
      },
      "ea20": {
        "flagged": 9438048.0,
        "total": 35995648.0
      },
      "ea21": {
        "flagged": 9269488.0,
        "total": 35995648.0
      },
      "ea22": {
        "flagged": 9696516.0,
        "total": 35995648.0
      },
      "ea23": {
        "flagged": 9619256.0,
        "total": 35995648.0
      },
      "ea24": {
        "flagged": 9253024.0,
        "total": 35995648.0
      },
      "ea25": {
        "flagged": 9249552.0,
        "total": 35995648.0
      },
      "ea26": {
        "flagged": 9360656.0,
        "total": 35995648.0
      },
      "ea27": {
        "flagged": 9306168.0,
        "total": 35995648.0
      }
    }
  },
  "field_J1436+2321": {
    "total": {
      "flagged": 293983796.0,
      "total": 652713984.0
    },
    "spw": {
      "0": {
        "flagged": 10219624.0,
        "total": 20397312.0
      },
      "1": {
        "flagged": 8345064.0,
        "total": 20397312.0
      },
      "10": {
        "flagged": 11233636.0,
        "total": 20397312.0
      },
      "11": {
        "flagged": 8287736.0,
        "total": 20397312.0
      },
      "12": {
        "flagged": 8279572.0,
        "total": 20397312.0
      },
      "13": {
        "flagged": 8277352.0,
        "total": 20397312.0
      },
      "14": {
        "flagged": 8271464.0,
        "total": 20397312.0
      },
      "15": {
        "flagged": 10158960.0,
        "total": 20397312.0
      },
      "16": {
        "flagged": 10805292.0,
        "total": 20397312.0
      },
      "17": {
        "flagged": 8965676.0,
        "total": 20397312.0
      },
      "18": {
        "flagged": 8995064.0,
        "total": 20397312.0
      },
      "19": {
        "flagged": 8995652.0,
        "total": 20397312.0
      },
      "2": {
        "flagged": 8297320.0,
        "total": 20397312.0
      },
      "20": {
        "flagged": 9058204.0,
        "total": 20397312.0
      },
      "21": {
        "flagged": 9113828.0,
        "total": 20397312.0
      },
      "22": {
        "flagged": 9219948.0,
        "total": 20397312.0
      },
      "23": {
        "flagged": 9841424.0,
        "total": 20397312.0
      },
      "24": {
        "flagged": 9907964.0,
        "total": 20397312.0
      },
      "25": {
        "flagged": 9516704.0,
        "total": 20397312.0
      },
      "26": {
        "flagged": 9105792.0,
        "total": 20397312.0
      },
      "27": {
        "flagged": 9444856.0,
        "total": 20397312.0
      },
      "28": {
        "flagged": 10185580.0,
        "total": 20397312.0
      },
      "29": {
        "flagged": 10784440.0,
        "total": 20397312.0
      },
      "3": {
        "flagged": 8320472.0,
        "total": 20397312.0
      },
      "30": {
        "flagged": 9424640.0,
        "total": 20397312.0
      },
      "31": {
        "flagged": 11091576.0,
        "total": 20397312.0
      },
      "4": {
        "flagged": 8308284.0,
        "total": 20397312.0
      },
      "5": {
        "flagged": 8364028.0,
        "total": 20397312.0
      },
      "6": {
        "flagged": 8315824.0,
        "total": 20397312.0
      },
      "7": {
        "flagged": 8299792.0,
        "total": 20397312.0
      },
      "8": {
        "flagged": 8276692.0,
        "total": 20397312.0
      },
      "9": {
        "flagged": 8271336.0,
        "total": 20397312.0
      }
    },
    "antenna": {
      "ea01": {
        "flagged": 22502008.0,
        "total": 48349184.0
      },
      "ea02": {
        "flagged": 22129424.0,
        "total": 48349184.0
      },
      "ea03": {
        "flagged": 21219196.0,
        "total": 48349184.0
      },
      "ea04": {
        "flagged": 21086092.0,
        "total": 48349184.0
      },
      "ea05": {
        "flagged": 20822624.0,
        "total": 48349184.0
      },
      "ea06": {
        "flagged": 32699980.0,
        "total": 48349184.0
      },
      "ea07": {
        "flagged": 23006924.0,
        "total": 48349184.0
      },
      "ea08": {
        "flagged": 21375220.0,
        "total": 48349184.0
      },
      "ea09": {
        "flagged": 21620844.0,
        "total": 48349184.0
      },
      "ea10": {
        "flagged": 20598436.0,
        "total": 48349184.0
      },
      "ea11": {
        "flagged": 21014392.0,
        "total": 48349184.0
      },
      "ea12": {
        "flagged": 21720324.0,
        "total": 48349184.0
      },
      "ea13": {
        "flagged": 20725732.0,
        "total": 48349184.0
      },
      "ea14": {
        "flagged": 22060908.0,
        "total": 48349184.0
      },
      "ea15": {
        "flagged": 20557632.0,
        "total": 48349184.0
      },
      "ea16": {
        "flagged": 22286404.0,
        "total": 48349184.0
      },
      "ea17": {
        "flagged": 20734336.0,
        "total": 48349184.0
      },
      "ea18": {
        "flagged": 20595552.0,
        "total": 48349184.0
      },
      "ea19": {
        "flagged": 21340960.0,
        "total": 48349184.0
      },
      "ea20": {
        "flagged": 20781904.0,
        "total": 48349184.0
      },
      "ea21": {
        "flagged": 21211704.0,
        "total": 48349184.0
      },
      "ea22": {
        "flagged": 21700440.0,
        "total": 48349184.0
      },
      "ea23": {
        "flagged": 21361824.0,
        "total": 48349184.0
      },
      "ea24": {
        "flagged": 21390964.0,
        "total": 48349184.0
      },
      "ea25": {
        "flagged": 21021432.0,
        "total": 48349184.0
      },
      "ea26": {
        "flagged": 20898984.0,
        "total": 48349184.0
      },
      "ea27": {
        "flagged": 21503352.0,
        "total": 48349184.0
      }
    }
  },
  "field_MS1455+2232": {
    "total": {
      "flagged": 742071968.0,
      "total": 3493601280.0
    },
    "spw": {
      "0": {
        "flagged": 30556265.0,
        "total": 109175040.0
      },
      "1": {
        "flagged": 16890365.0,
        "total": 109175040.0
      },
      "10": {
        "flagged": 37739127.0,
        "total": 109175040.0
      },
      "11": {
        "flagged": 16257144.0,
        "total": 109175040.0
      },
      "12": {
        "flagged": 16106281.0,
        "total": 109175040.0
      },
      "13": {
        "flagged": 16328557.0,
        "total": 109175040.0
      },
      "14": {
        "flagged": 16261150.0,
        "total": 109175040.0
      },
      "15": {
        "flagged": 30286792.0,
        "total": 109175040.0
      },
      "16": {
        "flagged": 36998360.0,
        "total": 109175040.0
      },
      "17": {
        "flagged": 23370949.0,
        "total": 109175040.0
      },
      "18": {
        "flagged": 23206493.0,
        "total": 109175040.0
      },
      "19": {
        "flagged": 23166093.0,
        "total": 109175040.0
      },
      "2": {
        "flagged": 16331954.0,
        "total": 109175040.0
      },
      "20": {
        "flagged": 23549823.0,
        "total": 109175040.0
      },
      "21": {
        "flagged": 24262305.0,
        "total": 109175040.0
      },
      "22": {
        "flagged": 25519903.0,
        "total": 109175040.0
      },
      "23": {
        "flagged": 26305770.0,
        "total": 109175040.0
      },
      "24": {
        "flagged": 26311067.0,
        "total": 109175040.0
      },
      "25": {
        "flagged": 25709181.0,
        "total": 109175040.0
      },
      "26": {
        "flagged": 25378814.0,
        "total": 109175040.0
      },
      "27": {
        "flagged": 25076433.0,
        "total": 109175040.0
      },
      "28": {
        "flagged": 28013101.0,
        "total": 109175040.0
      },
      "29": {
        "flagged": 32013399.0,
        "total": 109175040.0
      },
      "3": {
        "flagged": 16309273.0,
        "total": 109175040.0
      },
      "30": {
        "flagged": 25749937.0,
        "total": 109175040.0
      },
      "31": {
        "flagged": 35889894.0,
        "total": 109175040.0
      },
      "4": {
        "flagged": 16454558.0,
        "total": 109175040.0
      },
      "5": {
        "flagged": 16769443.0,
        "total": 109175040.0
      },
      "6": {
        "flagged": 16522545.0,
        "total": 109175040.0
      },
      "7": {
        "flagged": 16418737.0,
        "total": 109175040.0
      },
      "8": {
        "flagged": 16236690.0,
        "total": 109175040.0
      },
      "9": {
        "flagged": 16081565.0,
        "total": 109175040.0
      }
    },
    "antenna": {
      "ea01": {
        "flagged": 54793905.0,
        "total": 258785280.0
      },
      "ea02": {
        "flagged": 58749447.0,
        "total": 258785280.0
      },
      "ea03": {
        "flagged": 49270918.0,
        "total": 258785280.0
      },
      "ea04": {
        "flagged": 52973480.0,
        "total": 258785280.0
      },
      "ea05": {
        "flagged": 49551320.0,
        "total": 258785280.0
      },
      "ea06": {
        "flagged": 147483977.0,
        "total": 258785280.0
      },
      "ea07": {
        "flagged": 59286783.0,
        "total": 258785280.0
      },
      "ea08": {
        "flagged": 49296479.0,
        "total": 258785280.0
      },
      "ea09": {
        "flagged": 55658933.0,
        "total": 258785280.0
      },
      "ea10": {
        "flagged": 47994764.0,
        "total": 258785280.0
      },
      "ea11": {
        "flagged": 49037179.0,
        "total": 258785280.0
      },
      "ea12": {
        "flagged": 49047951.0,
        "total": 258785280.0
      },
      "ea13": {
        "flagged": 47391477.0,
        "total": 258785280.0
      },
      "ea14": {
        "flagged": 56918882.0,
        "total": 258785280.0
      },
      "ea15": {
        "flagged": 49242432.0,
        "total": 258785280.0
      },
      "ea16": {
        "flagged": 57662304.0,
        "total": 258785280.0
      },
      "ea17": {
        "flagged": 48955105.0,
        "total": 258785280.0
      },
      "ea18": {
        "flagged": 50082823.0,
        "total": 258785280.0
      },
      "ea19": {
        "flagged": 47047927.0,
        "total": 258785280.0
      },
      "ea20": {
        "flagged": 50718276.0,
        "total": 258785280.0
      },
      "ea21": {
        "flagged": 47673317.0,
        "total": 258785280.0
      },
      "ea22": {
        "flagged": 50852092.0,
        "total": 258785280.0
      },
      "ea23": {
        "flagged": 48711961.0,
        "total": 258785280.0
      },
      "ea24": {
        "flagged": 49440278.0,
        "total": 258785280.0
      },
      "ea25": {
        "flagged": 47430143.0,
        "total": 258785280.0
      },
      "ea26": {
        "flagged": 58367183.0,
        "total": 258785280.0
      },
      "ea27": {
        "flagged": 50504600.0,
        "total": 258785280.0
      }
    }
  },
  "field_J1616+0459": {
    "total": {
      "flagged": 268028784.0,
      "total": 451436544.0
    },
    "spw": {
      "0": {
        "flagged": 8709048.0,
        "total": 14107392.0
      },
      "1": {
        "flagged": 7709100.0,
        "total": 14107392.0
      },
      "10": {
        "flagged": 9326684.0,
        "total": 14107392.0
      },
      "11": {
        "flagged": 7656984.0,
        "total": 14107392.0
      },
      "12": {
        "flagged": 7651960.0,
        "total": 14107392.0
      },
      "13": {
        "flagged": 7647540.0,
        "total": 14107392.0
      },
      "14": {
        "flagged": 7650488.0,
        "total": 14107392.0
      },
      "15": {
        "flagged": 8652920.0,
        "total": 14107392.0
      },
      "16": {
        "flagged": 9060576.0,
        "total": 14107392.0
      },
      "17": {
        "flagged": 8125928.0,
        "total": 14107392.0
      },
      "18": {
        "flagged": 8124688.0,
        "total": 14107392.0
      },
      "19": {
        "flagged": 8121008.0,
        "total": 14107392.0
      },
      "2": {
        "flagged": 7670612.0,
        "total": 14107392.0
      },
      "20": {
        "flagged": 8151968.0,
        "total": 14107392.0
      },
      "21": {
        "flagged": 8289708.0,
        "total": 14107392.0
      },
      "22": {
        "flagged": 8558220.0,
        "total": 14107392.0
      },
      "23": {
        "flagged": 9090612.0,
        "total": 14107392.0
      },
      "24": {
        "flagged": 8931176.0,
        "total": 14107392.0
      },
      "25": {
        "flagged": 8636404.0,
        "total": 14107392.0
      },
      "26": {
        "flagged": 8602172.0,
        "total": 14107392.0
      },
      "27": {
        "flagged": 8462156.0,
        "total": 14107392.0
      },
      "28": {
        "flagged": 8795248.0,
        "total": 14107392.0
      },
      "29": {
        "flagged": 9756884.0,
        "total": 14107392.0
      },
      "3": {
        "flagged": 7680528.0,
        "total": 14107392.0
      },
      "30": {
        "flagged": 10240912.0,
        "total": 14107392.0
      },
      "31": {
        "flagged": 10712868.0,
        "total": 14107392.0
      },
      "4": {
        "flagged": 7670764.0,
        "total": 14107392.0
      },
      "5": {
        "flagged": 7704120.0,
        "total": 14107392.0
      },
      "6": {
        "flagged": 7673064.0,
        "total": 14107392.0
      },
      "7": {
        "flagged": 7665608.0,
        "total": 14107392.0
      },
      "8": {
        "flagged": 7649868.0,
        "total": 14107392.0
      },
      "9": {
        "flagged": 7648968.0,
        "total": 14107392.0
      }
    },
    "antenna": {
      "ea01": {
        "flagged": 19694176.0,
        "total": 33439744.0
      },
      "ea02": {
        "flagged": 20173032.0,
        "total": 33439744.0
      },
      "ea03": {
        "flagged": 19577580.0,
        "total": 33439744.0
      },
      "ea04": {
        "flagged": 20199036.0,
        "total": 33439744.0
      },
      "ea05": {
        "flagged": 19747648.0,
        "total": 33439744.0
      },
      "ea06": {
        "flagged": 26041304.0,
        "total": 33439744.0
      },
      "ea07": {
        "flagged": 20559820.0,
        "total": 33439744.0
      },
      "ea08": {
        "flagged": 19175160.0,
        "total": 33439744.0
      },
      "ea09": {
        "flagged": 20018144.0,
        "total": 33439744.0
      },
      "ea10": {
        "flagged": 19095980.0,
        "total": 33439744.0
      },
      "ea11": {
        "flagged": 19260332.0,
        "total": 33439744.0
      },
      "ea12": {
        "flagged": 19725260.0,
        "total": 33439744.0
      },
      "ea13": {
        "flagged": 19155208.0,
        "total": 33439744.0
      },
      "ea14": {
        "flagged": 20152808.0,
        "total": 33439744.0
      },
      "ea15": {
        "flagged": 18922344.0,
        "total": 33439744.0
      },
      "ea16": {
        "flagged": 20073440.0,
        "total": 33439744.0
      },
      "ea17": {
        "flagged": 18970188.0,
        "total": 33439744.0
      },
      "ea18": {
        "flagged": 19054292.0,
        "total": 33439744.0
      },
      "ea19": {
        "flagged": 19146820.0,
        "total": 33439744.0
      },
      "ea20": {
        "flagged": 19407848.0,
        "total": 33439744.0
      },
      "ea21": {
        "flagged": 18941796.0,
        "total": 33439744.0
      },
      "ea22": {
        "flagged": 20222460.0,
        "total": 33439744.0
      },
      "ea23": {
        "flagged": 19794956.0,
        "total": 33439744.0
      },
      "ea24": {
        "flagged": 18843428.0,
        "total": 33439744.0
      },
      "ea25": {
        "flagged": 18978560.0,
        "total": 33439744.0
      },
      "ea26": {
        "flagged": 21737768.0,
        "total": 33439744.0
      },
      "ea27": {
        "flagged": 19388180.0,
        "total": 33439744.0
      }
    }
  },
  "field_A2204": {
    "total": {
      "flagged": 869294602.0,
      "total": 3663249408.0
    },
    "spw": {
      "0": {
        "flagged": 31572586.0,
        "total": 114476544.0
      },
      "1": {
        "flagged": 17159078.0,
        "total": 114476544.0
      },
      "10": {
        "flagged": 40192247.0,
        "total": 114476544.0
      },
      "11": {
        "flagged": 16442450.0,
        "total": 114476544.0
      },
      "12": {
        "flagged": 16278452.0,
        "total": 114476544.0
      },
      "13": {
        "flagged": 16486788.0,
        "total": 114476544.0
      },
      "14": {
        "flagged": 16445894.0,
        "total": 114476544.0
      },
      "15": {
        "flagged": 31266240.0,
        "total": 114476544.0
      },
      "16": {
        "flagged": 37437166.0,
        "total": 114476544.0
      },
      "17": {
        "flagged": 23797498.0,
        "total": 114476544.0
      },
      "18": {
        "flagged": 23697948.0,
        "total": 114476544.0
      },
      "19": {
        "flagged": 23636688.0,
        "total": 114476544.0
      },
      "2": {
        "flagged": 16527355.0,
        "total": 114476544.0
      },
      "20": {
        "flagged": 24068024.0,
        "total": 114476544.0
      },
      "21": {
        "flagged": 26595809.0,
        "total": 114476544.0
      },
      "22": {
        "flagged": 31865525.0,
        "total": 114476544.0
      },
      "23": {
        "flagged": 39058656.0,
        "total": 114476544.0
      },
      "24": {
        "flagged": 36692239.0,
        "total": 114476544.0
      },
      "25": {
        "flagged": 32225055.0,
        "total": 114476544.0
      },
      "26": {
        "flagged": 28927562.0,
        "total": 114476544.0
      },
      "27": {
        "flagged": 29356996.0,
        "total": 114476544.0
      },
      "28": {
        "flagged": 33474707.0,
        "total": 114476544.0
      },
      "29": {
        "flagged": 46262113.0,
        "total": 114476544.0
      },
      "3": {
        "flagged": 16502577.0,
        "total": 114476544.0
      },
      "30": {
        "flagged": 53212005.0,
        "total": 114476544.0
      },
      "31": {
        "flagged": 60658346.0,
        "total": 114476544.0
      },
      "4": {
        "flagged": 16621325.0,
        "total": 114476544.0
      },
      "5": {
        "flagged": 16897016.0,
        "total": 114476544.0
      },
      "6": {
        "flagged": 16692408.0,
        "total": 114476544.0
      },
      "7": {
        "flagged": 16621576.0,
        "total": 114476544.0
      },
      "8": {
        "flagged": 16392374.0,
        "total": 114476544.0
      },
      "9": {
        "flagged": 16229899.0,
        "total": 114476544.0
      }
    },
    "antenna": {
      "ea01": {
        "flagged": 56305182.0,
        "total": 271351808.0
      },
      "ea02": {
        "flagged": 72431544.0,
        "total": 271351808.0
      },
      "ea03": {
        "flagged": 62227458.0,
        "total": 271351808.0
      },
      "ea04": {
        "flagged": 69661232.0,
        "total": 271351808.0
      },
      "ea05": {
        "flagged": 64268696.0,
        "total": 271351808.0
      },
      "ea06": {
        "flagged": 159567041.0,
        "total": 271351808.0
      },
      "ea07": {
        "flagged": 73324385.0,
        "total": 271351808.0
      },
      "ea08": {
        "flagged": 55115205.0,
        "total": 271351808.0
      },
      "ea09": {
        "flagged": 67910235.0,
        "total": 271351808.0
      },
      "ea10": {
        "flagged": 53861114.0,
        "total": 271351808.0
      },
      "ea11": {
        "flagged": 58753475.0,
        "total": 271351808.0
      },
      "ea12": {
        "flagged": 57398989.0,
        "total": 271351808.0
      },
      "ea13": {
        "flagged": 51593154.0,
        "total": 271351808.0
      },
      "ea14": {
        "flagged": 71187188.0,
        "total": 271351808.0
      },
      "ea15": {
        "flagged": 53773650.0,
        "total": 271351808.0
      },
      "ea16": {
        "flagged": 69900589.0,
        "total": 271351808.0
      },
      "ea17": {
        "flagged": 53469888.0,
        "total": 271351808.0
      },
      "ea18": {
        "flagged": 54314604.0,
        "total": 271351808.0
      },
      "ea19": {
        "flagged": 52269912.0,
        "total": 271351808.0
      },
      "ea20": {
        "flagged": 63560152.0,
        "total": 271351808.0
      },
      "ea21": {
        "flagged": 50532805.0,
        "total": 271351808.0
      },
      "ea22": {
        "flagged": 68450449.0,
        "total": 271351808.0
      },
      "ea23": {
        "flagged": 62307350.0,
        "total": 271351808.0
      },
      "ea24": {
        "flagged": 50498533.0,
        "total": 271351808.0
      },
      "ea25": {
        "flagged": 52467159.0,
        "total": 271351808.0
      },
      "ea26": {
        "flagged": 79909331.0,
        "total": 271351808.0
      },
      "ea27": {
        "flagged": 53529884.0,
        "total": 271351808.0
      }
    }
  },
  "field_J1719+1745": {
    "total": {
      "flagged": 320986676.0,
      "total": 540573696.0
    },
    "spw": {
      "0": {
        "flagged": 10589580.0,
        "total": 16892928.0
      },
      "1": {
        "flagged": 9427856.0,
        "total": 16892928.0
      },
      "10": {
        "flagged": 11633812.0,
        "total": 16892928.0
      },
      "11": {
        "flagged": 9876216.0,
        "total": 16892928.0
      },
      "12": {
        "flagged": 9395376.0,
        "total": 16892928.0
      },
      "13": {
        "flagged": 9393276.0,
        "total": 16892928.0
      },
      "14": {
        "flagged": 9397104.0,
        "total": 16892928.0
      },
      "15": {
        "flagged": 10560572.0,
        "total": 16892928.0
      },
      "16": {
        "flagged": 11039060.0,
        "total": 16892928.0
      },
      "17": {
        "flagged": 9946484.0,
        "total": 16892928.0
      },
      "18": {
        "flagged": 9945180.0,
        "total": 16892928.0
      },
      "19": {
        "flagged": 9943172.0,
        "total": 16892928.0
      },
      "2": {
        "flagged": 9403596.0,
        "total": 16892928.0
      },
      "20": {
        "flagged": 9978556.0,
        "total": 16892928.0
      },
      "21": {
        "flagged": 10047920.0,
        "total": 16892928.0
      },
      "22": {
        "flagged": 10190864.0,
        "total": 16892928.0
      },
      "23": {
        "flagged": 10338992.0,
        "total": 16892928.0
      },
      "24": {
        "flagged": 10359768.0,
        "total": 16892928.0
      },
      "25": {
        "flagged": 10130884.0,
        "total": 16892928.0
      },
      "26": {
        "flagged": 10083036.0,
        "total": 16892928.0
      },
      "27": {
        "flagged": 10104768.0,
        "total": 16892928.0
      },
      "28": {
        "flagged": 10628920.0,
        "total": 16892928.0
      },
      "29": {
        "flagged": 10870444.0,
        "total": 16892928.0
      },
      "3": {
        "flagged": 9417952.0,
        "total": 16892928.0
      },
      "30": {
        "flagged": 10410084.0,
        "total": 16892928.0
      },
      "31": {
        "flagged": 11383140.0,
        "total": 16892928.0
      },
      "4": {
        "flagged": 9415832.0,
        "total": 16892928.0
      },
      "5": {
        "flagged": 9456228.0,
        "total": 16892928.0
      },
      "6": {
        "flagged": 9420516.0,
        "total": 16892928.0
      },
      "7": {
        "flagged": 9408780.0,
        "total": 16892928.0
      },
      "8": {
        "flagged": 9395560.0,
        "total": 16892928.0
      },
      "9": {
        "flagged": 9393148.0,
        "total": 16892928.0
      }
    },
    "antenna": {
      "ea01": {
        "flagged": 24110896.0,
        "total": 40042496.0
      },
      "ea02": {
        "flagged": 23990344.0,
        "total": 40042496.0
      },
      "ea03": {
        "flagged": 23187040.0,
        "total": 40042496.0
      },
      "ea04": {
        "flagged": 24080832.0,
        "total": 40042496.0
      },
      "ea05": {
        "flagged": 23985416.0,
        "total": 40042496.0
      },
      "ea06": {
        "flagged": 31525596.0,
        "total": 40042496.0
      },
      "ea07": {
        "flagged": 23963536.0,
        "total": 40042496.0
      },
      "ea08": {
        "flagged": 23106396.0,
        "total": 40042496.0
      },
      "ea09": {
        "flagged": 23860860.0,
        "total": 40042496.0
      },
      "ea10": {
        "flagged": 23054072.0,
        "total": 40042496.0
      },
      "ea11": {
        "flagged": 23147932.0,
        "total": 40042496.0
      },
      "ea12": {
        "flagged": 23062900.0,
        "total": 40042496.0
      },
      "ea13": {
        "flagged": 23540668.0,
        "total": 40042496.0
      },
      "ea14": {
        "flagged": 23929068.0,
        "total": 40042496.0
      },
      "ea15": {
        "flagged": 23530372.0,
        "total": 40042496.0
      },
      "ea16": {
        "flagged": 23991540.0,
        "total": 40042496.0
      },
      "ea17": {
        "flagged": 23084060.0,
        "total": 40042496.0
      },
      "ea18": {
        "flagged": 24080664.0,
        "total": 40042496.0
      },
      "ea19": {
        "flagged": 22973948.0,
        "total": 40042496.0
      },
      "ea20": {
        "flagged": 23210284.0,
        "total": 40042496.0
      },
      "ea21": {
        "flagged": 22947240.0,
        "total": 40042496.0
      },
      "ea22": {
        "flagged": 23654812.0,
        "total": 40042496.0
      },
      "ea23": {
        "flagged": 23232844.0,
        "total": 40042496.0
      },
      "ea24": {
        "flagged": 23004440.0,
        "total": 40042496.0
      },
      "ea25": {
        "flagged": 22946524.0,
        "total": 40042496.0
      },
      "ea26": {
        "flagged": 23779376.0,
        "total": 40042496.0
      },
      "ea27": {
        "flagged": 22991692.0,
        "total": 40042496.0
      }
    }
  },
  "field_RXJ1720+2638": {
    "total": {
      "flagged": 823958637.0,
      "total": 3559735296.0
    },
    "spw": {
      "0": {
        "flagged": 32803741.0,
        "total": 111241728.0
      },
      "1": {
        "flagged": 19037321.0,
        "total": 111241728.0
      },
      "10": {
        "flagged": 44089688.0,
        "total": 111241728.0
      },
      "11": {
        "flagged": 23828146.0,
        "total": 111241728.0
      },
      "12": {
        "flagged": 18235055.0,
        "total": 111241728.0
      },
      "13": {
        "flagged": 18511233.0,
        "total": 111241728.0
      },
      "14": {
        "flagged": 18494733.0,
        "total": 111241728.0
      },
      "15": {
        "flagged": 32559335.0,
        "total": 111241728.0
      },
      "16": {
        "flagged": 38974669.0,
        "total": 111241728.0
      },
      "17": {
        "flagged": 25352647.0,
        "total": 111241728.0
      },
      "18": {
        "flagged": 25236663.0,
        "total": 111241728.0
      },
      "19": {
        "flagged": 25184350.0,
        "total": 111241728.0
      },
      "2": {
        "flagged": 18429077.0,
        "total": 111241728.0
      },
      "20": {
        "flagged": 25657674.0,
        "total": 111241728.0
      },
      "21": {
        "flagged": 26342258.0,
        "total": 111241728.0
      },
      "22": {
        "flagged": 27534210.0,
        "total": 111241728.0
      },
      "23": {
        "flagged": 28151828.0,
        "total": 111241728.0
      },
      "24": {
        "flagged": 28649394.0,
        "total": 111241728.0
      },
      "25": {
        "flagged": 27662399.0,
        "total": 111241728.0
      },
      "26": {
        "flagged": 26792087.0,
        "total": 111241728.0
      },
      "27": {
        "flagged": 26992299.0,
        "total": 111241728.0
      },
      "28": {
        "flagged": 31180624.0,
        "total": 111241728.0
      },
      "29": {
        "flagged": 34872917.0,
        "total": 111241728.0
      },
      "3": {
        "flagged": 18401747.0,
        "total": 111241728.0
      },
      "30": {
        "flagged": 28929579.0,
        "total": 111241728.0
      },
      "31": {
        "flagged": 40968368.0,
        "total": 111241728.0
      },
      "4": {
        "flagged": 18551516.0,
        "total": 111241728.0
      },
      "5": {
        "flagged": 18810704.0,
        "total": 111241728.0
      },
      "6": {
        "flagged": 18613565.0,
        "total": 111241728.0
      },
      "7": {
        "flagged": 18573670.0,
        "total": 111241728.0
      },
      "8": {
        "flagged": 18357034.0,
        "total": 111241728.0
      },
      "9": {
        "flagged": 18180106.0,
        "total": 111241728.0
      }
    },
    "antenna": {
      "ea01": {
        "flagged": 60777344.0,
        "total": 263684096.0
      },
      "ea02": {
        "flagged": 65051421.0,
        "total": 263684096.0
      },
      "ea03": {
        "flagged": 54293560.0,
        "total": 263684096.0
      },
      "ea04": {
        "flagged": 58766024.0,
        "total": 263684096.0
      },
      "ea05": {
        "flagged": 56401407.0,
        "total": 263684096.0
      },
      "ea06": {
        "flagged": 158550030.0,
        "total": 263684096.0
      },
      "ea07": {
        "flagged": 69680622.0,
        "total": 263684096.0
      },
      "ea08": {
        "flagged": 55408454.0,
        "total": 263684096.0
      },
      "ea09": {
        "flagged": 61193636.0,
        "total": 263684096.0
      },
      "ea10": {
        "flagged": 53054051.0,
        "total": 263684096.0
      },
      "ea11": {
        "flagged": 54459357.0,
        "total": 263684096.0
      },
      "ea12": {
        "flagged": 53925235.0,
        "total": 263684096.0
      },
      "ea13": {
        "flagged": 52612630.0,
        "total": 263684096.0
      },
      "ea14": {
        "flagged": 63643679.0,
        "total": 263684096.0
      },
      "ea15": {
        "flagged": 55249170.0,
        "total": 263684096.0
      },
      "ea16": {
        "flagged": 63857426.0,
        "total": 263684096.0
      },
      "ea17": {
        "flagged": 56832621.0,
        "total": 263684096.0
      },
      "ea18": {
        "flagged": 62456016.0,
        "total": 263684096.0
      },
      "ea19": {
        "flagged": 51989021.0,
        "total": 263684096.0
      },
      "ea20": {
        "flagged": 56837222.0,
        "total": 263684096.0
      },
      "ea21": {
        "flagged": 53099927.0,
        "total": 263684096.0
      },
      "ea22": {
        "flagged": 55731716.0,
        "total": 263684096.0
      },
      "ea23": {
        "flagged": 53682868.0,
        "total": 263684096.0
      },
      "ea24": {
        "flagged": 54504261.0,
        "total": 263684096.0
      },
      "ea25": {
        "flagged": 53782604.0,
        "total": 263684096.0
      },
      "ea26": {
        "flagged": 57537389.0,
        "total": 263684096.0
      },
      "ea27": {
        "flagged": 54539583.0,
        "total": 263684096.0
      }
    }
  }
}